fortmes_pypi/__init__.py
fortmes_pypi/api_client.py
fortmes_pypi/auth.py
tests/__init__.py
tests/test_auth0_device_auth.py
fortmes.pypi-0.1.21.dist-info/LICENSE
fortmes.pypi-0.1.21.dist-info/METADATA
fortmes.pypi-0.1.21.dist-info/WHEEL
fortmes.pypi-0.1.21.dist-info/top_level.txt
fortmes.pypi-0.1.21.dist-info/RECORD
