Metadata-Version: 2.1
Name: fortmes.pypi
Version: 0.1.21
Summary: Python package for fortmes login
License: MIT License
Project-URL: documentation, https://github.com/fortmes/fortmes-pypi
Project-URL: homepage, https://github.com/fortmes/fortmes-pypi
Project-URL: repository, https://github.com/fortmes/fortmes-pypi
Requires-Python: >=3.11
License-File: LICENSE
